odoo/addons/product_expiry_configurable/README.rst
odoo/addons/product_expiry_configurable/__init__.py
odoo/addons/product_expiry_configurable/__manifest__.py
odoo/addons/product_expiry_configurable/data/product_expiry_data.xml
odoo/addons/product_expiry_configurable/i18n/es.po
odoo/addons/product_expiry_configurable/i18n/it.po
odoo/addons/product_expiry_configurable/i18n/product_expiry_configurable.pot
odoo/addons/product_expiry_configurable/migrations/16.0.1.0.0/post-migrate.py
odoo/addons/product_expiry_configurable/migrations/16.0.1.0.0/pre-migrate.py
odoo/addons/product_expiry_configurable/models/__init__.py
odoo/addons/product_expiry_configurable/models/product_category.py
odoo/addons/product_expiry_configurable/models/product_template.py
odoo/addons/product_expiry_configurable/models/stock_lot.py
odoo/addons/product_expiry_configurable/readme/CONFIGURE.rst
odoo/addons/product_expiry_configurable/readme/CONTRIBUTORS.rst
odoo/addons/product_expiry_configurable/readme/DESCRIPTION.rst
odoo/addons/product_expiry_configurable/static/description/icon.png
odoo/addons/product_expiry_configurable/static/description/index.html
odoo/addons/product_expiry_configurable/static/images/category.png
odoo/addons/product_expiry_configurable/static/images/crons.png
odoo/addons/product_expiry_configurable/tests/__init__.py
odoo/addons/product_expiry_configurable/tests/common.py
odoo/addons/product_expiry_configurable/tests/test_product_category.py
odoo/addons/product_expiry_configurable/tests/test_product_template.py
odoo/addons/product_expiry_configurable/tests/test_stock_production_lot.py
odoo/addons/product_expiry_configurable/views/product_category.xml
odoo/addons/product_expiry_configurable/views/stock_lot.xml
odoo_addon_product_expiry_configurable-16.0.1.0.0.13.dist-info/METADATA
odoo_addon_product_expiry_configurable-16.0.1.0.0.13.dist-info/WHEEL
odoo_addon_product_expiry_configurable-16.0.1.0.0.13.dist-info/top_level.txt
odoo_addon_product_expiry_configurable-16.0.1.0.0.13.dist-info/RECORD
