Metadata-Version: 2.1
Name: odoo-addon-product_expiry_configurable
Version: 16.0.1.0.0.13
Summary: This model allows setting expiry times on category and to use the 'end_of_life' date for the computation of lot dates
Home-page: https://github.com/OCA/product-attribute
Author: Odoo Community Association (OCA)
Author-email: support@odoo-community.org
License: AGPL-3
Classifier: Programming Language :: Python
Classifier: Framework :: Odoo
Classifier: Framework :: Odoo :: 16.0
Classifier: License :: OSI Approved :: GNU Affero General Public License v3
Requires-Python: >=3.10
Requires-Dist: odoo <16.1dev,>=16.0a
